om_quant_fin/__init__.py
om_quant_fin/om_quant_fin.py
om_quant_fin-1.1.0.dist-info/METADATA
om_quant_fin-1.1.0.dist-info/WHEEL
om_quant_fin-1.1.0.dist-info/top_level.txt
om_quant_fin-1.1.0.dist-info/RECORD
