Metadata-Version: 2.1
Name: om-quant-fin
Version: 1.1.0
Summary: The Outspoken Market is training the next quantitative generation. OM Quant Fin is a modern Python package for quantitative trading analysis. Our mission is to make your quant life easier and more accurate.
Home-page: UNKNOWN
Author: Outspoken Market
Author-email: info@outspokenmarket.com
License: UNKNOWN
Platform: UNKNOWN
Classifier: Development Status :: 4 - Beta
Classifier: License :: OSI Approved :: MIT License
Classifier: Programming Language :: Python :: 3
Classifier: Programming Language :: Python :: 3.6
Classifier: Programming Language :: Python :: 3.7
Classifier: Programming Language :: Python :: 3.8
Requires-Dist: yfinance
Requires-Dist: pandas
Requires-Dist: scikit-learn
Requires-Dist: numpy
Requires-Dist: time
Requires-Dist: sys
Requires-Dist: plotly
Requires-Dist: statsmodels.tsa.stattools
Requires-Dist: numpy-ext
Requires-Dist: warnings
Requires-Dist: datetime
